ddnp/__init__.py
ddnp/__main__.py
ddnp/app.py
ddnp/env.py
ddnp/vol.py
ddnp-1.0.1.dist-info/LICENSE.txt
ddnp-1.0.1.dist-info/METADATA
ddnp-1.0.1.dist-info/WHEEL
ddnp-1.0.1.dist-info/top_level.txt
ddnp-1.0.1.dist-info/RECORD
