Metadata-Version: 2.1
Name: ddnp
Version: 1.0.1
Summary: Docker Data Network Proxy
Home-page: https://github.com/al-niessner/DCP
Author: Al Niessner
Author-email: Al.Niessner@jpl.nasa.gov
License: see LICENSE file for details
Keywords: docker data network proxy copy secret environment
Platform: UNKNOWN
Classifier: Programming Language :: Python :: 3
Classifier: Operating System :: OS Independent
Classifier: License :: Free To Use But Restricted
Classifier: Development Status :: 5 - Production/Stable
Requires-Dist: flask
